turborest/__init__.py
turborest/__main__.py
turborest/client.py
turborest/logger.py
turborest/cmd/__init__.py
turborest/cmd/ping.py
turborest-0.1.7.dist-info/METADATA
turborest-0.1.7.dist-info/WHEEL
turborest-0.1.7.dist-info/top_level.txt
turborest-0.1.7.dist-info/RECORD
