Metadata-Version: 2.1
Name: turborest
Version: 0.1.7
Summary: A library for monitoring files and directories for changes
Home-page: https://github.com/bytesentinel-io/turborest
Author: ByteSentinel.io
Author-email: dev@bytesentinel.io
Classifier: Programming Language :: Python :: 3
Classifier: License :: OSI Approved :: MIT License
Classifier: Operating System :: OS Independent
Requires-Python: >=3.7
Requires-Dist: fibertrace >=0.1.5
